skmultilearn/__init__.py
skmultilearn/dataset.py
skmultilearn/utils.py
skmultilearn/adapt/__init__.py
skmultilearn/adapt/brknn.py
skmultilearn/adapt/mlaram.py
skmultilearn/adapt/mlknn.py
skmultilearn/adapt/mltsvm.py
skmultilearn/base/__init__.py
skmultilearn/base/base.py
skmultilearn/base/mock.py
skmultilearn/base/problem_transformation.py
skmultilearn/cluster/__init__.py
skmultilearn/cluster/balancedkmeans.py
skmultilearn/cluster/base.py
skmultilearn/cluster/fixed.py
skmultilearn/cluster/graphtool.py
skmultilearn/cluster/helpers.py
skmultilearn/cluster/igraph.py
skmultilearn/cluster/matrix.py
skmultilearn/cluster/networkx.py
skmultilearn/cluster/random.py
skmultilearn/embedding/__init__.py
skmultilearn/embedding/_mdsw.py
skmultilearn/embedding/classifier.py
skmultilearn/embedding/clems.py
skmultilearn/embedding/openne.py
skmultilearn/embedding/skembeddings.py
skmultilearn/embedding/unit_tests/__init__.py
skmultilearn/embedding/unit_tests/test_classifier.py
skmultilearn/ensemble/__init__.py
skmultilearn/ensemble/partition.py
skmultilearn/ensemble/rakeld.py
skmultilearn/ensemble/rakelo.py
skmultilearn/ensemble/voting.py
skmultilearn/ext/__init__.py
skmultilearn/ext/keras.py
skmultilearn/ext/meka.py
skmultilearn/missing/__init__.py
skmultilearn/missing/functions.py
skmultilearn/missing/smile.py
skmultilearn/model_selection/__init__.py
skmultilearn/model_selection/iterative_stratification.py
skmultilearn/model_selection/measures.py
skmultilearn/problem_transform/__init__.py
skmultilearn/problem_transform/br.py
skmultilearn/problem_transform/cc.py
skmultilearn/problem_transform/chf.py
skmultilearn/problem_transform/gsc.py
skmultilearn/problem_transform/iblr.py
skmultilearn/problem_transform/lp.py
skmultilearn/problem_transform/pcc.py
skmultilearn/tree/__init__.py
skmultilearn/tree/pct.py
scikit_multilearn_ng-0.0.8.dist-info/LICENSE
scikit_multilearn_ng-0.0.8.dist-info/METADATA
scikit_multilearn_ng-0.0.8.dist-info/WHEEL
scikit_multilearn_ng-0.0.8.dist-info/top_level.txt
scikit_multilearn_ng-0.0.8.dist-info/RECORD
