Metadata-Version: 2.1
Name: scikit-multilearn-ng
Version: 0.0.8
Summary: Scikit-multilearn-ng is the follow up to scikit-multilearn, a BSD-licensed library for multi-label classification that is built on top of the well-known scikit-learn ecosystem.
Home-page: https://github.com/scikit-multilearn-ng/scikit-multilearn-ng/
Author: Piotr Szymański
Author-email: niedakh@gmail.com
License: BSD
Classifier: Development Status :: 5 - Production/Stable
Classifier: Environment :: Console
Classifier: Environment :: Web Environment
Classifier: Intended Audience :: Developers
Classifier: Intended Audience :: Education
Classifier: Intended Audience :: Science/Research
Classifier: License :: OSI Approved :: BSD License
Classifier: Operating System :: MacOS :: MacOS X
Classifier: Operating System :: Microsoft :: Windows
Classifier: Operating System :: POSIX
Classifier: Programming Language :: Python
Classifier: Topic :: Scientific/Engineering
Classifier: Topic :: Scientific/Engineering :: Information Analysis
Classifier: Topic :: Scientific/Engineering :: Bio-Informatics
License-File: LICENSE
Requires-Dist: scipy >=1.1.0
Requires-Dist: numpy >=1.15.1
Requires-Dist: liac-arff >=2.2.1
Requires-Dist: networkx >=2.1
Requires-Dist: python-louvain >=0.11
Requires-Dist: future >=0.16.0
Requires-Dist: scikit-learn >=0.19.2
Requires-Dist: requests >=2.18.4
Requires-Dist: joblib
Provides-Extra: dev
Requires-Dist: pytest >=3.3.1 ; extra == 'dev'
Requires-Dist: PyHamcrest >=1.9.0 ; extra == 'dev'
Requires-Dist: ipython ; extra == 'dev'
Requires-Dist: ipython-genutils ; extra == 'dev'
Provides-Extra: gpl
Requires-Dist: igraph ; extra == 'gpl'
Provides-Extra: keras
Requires-Dist: keras <=2.12.0 ; extra == 'keras'
Requires-Dist: tensorflow ; extra == 'keras'
Provides-Extra: test
Requires-Dist: pytest ; extra == 'test'
Requires-Dist: pyhamcrest ; extra == 'test'
